intake_sqlite/__init__.py
intake_sqlite/sqlite_cat.py
intake_sqlite/sqlite_src.py
intake_sqlite-0.2.0.dist-info/LICENSE.txt
intake_sqlite-0.2.0.dist-info/METADATA
intake_sqlite-0.2.0.dist-info/WHEEL
intake_sqlite-0.2.0.dist-info/entry_points.txt
intake_sqlite-0.2.0.dist-info/top_level.txt
intake_sqlite-0.2.0.dist-info/RECORD
