Metadata-Version: 2.1
Name: intake-sqlite
Version: 0.2.0
Summary: An Intake driver to access local or remote SQLite databases by URL.
Home-page: https://github.com/catalyst-cooperative/intake-sqlite
Author: Catalyst Cooperative
Author-email: pudl@catalyst.coop
Maintainer: Zane Selvans
Maintainer-email: zane.selvans@catalyst.coop
License: MIT
Project-URL: Source, https://github.com/catalyst-cooperative/intake-sqlite
Project-URL: Documentation, https://intake-sqlite.readthedocs.io
Project-URL: Issue Tracker, https://github.com/catalyst-cooperative/intake-sqlite/issues
Keywords: intake,sqlite,data catalog
Classifier: Development Status :: 3 - Alpha
Classifier: Environment :: Console
Classifier: License :: OSI Approved :: MIT License
Classifier: Natural Language :: English
Classifier: Operating System :: OS Independent
Classifier: Programming Language :: Python
Classifier: Programming Language :: Python :: 3
Classifier: Programming Language :: Python :: 3 :: Only
Classifier: Programming Language :: Python :: 3.8
Classifier: Programming Language :: Python :: 3.9
Classifier: Programming Language :: Python :: 3.10
Classifier: Programming Language :: Python :: 3.11
Requires-Python: >=3.8,<3.12
License-File: LICENSE.txt
Requires-Dist: intake-sql (<0.4,>=0.3.1)
Requires-Dist: fsspec (<2023,>=2022.5)
Provides-Extra: dev
Requires-Dist: black (<23,>=22) ; extra == 'dev'
Requires-Dist: isort (<6,>=5) ; extra == 'dev'
Requires-Dist: tox (<4,>=3.20) ; extra == 'dev'
Requires-Dist: twine (<5.0,>=3.3) ; extra == 'dev'
Provides-Extra: docs
Requires-Dist: doc8 (<1.1,>=0.9) ; extra == 'docs'
Requires-Dist: furo (>=2022.4.7) ; extra == 'docs'
Requires-Dist: sphinx (<6,>=4) ; extra == 'docs'
Requires-Dist: sphinx-autoapi (<3,>=1.8) ; extra == 'docs'
Requires-Dist: sphinx-issues (<4.0,>=1.2) ; extra == 'docs'
Provides-Extra: tests
Requires-Dist: bandit (<2,>=1.6) ; extra == 'tests'
Requires-Dist: coverage (<7,>=5.3) ; extra == 'tests'
Requires-Dist: doc8 (<1.1,>=0.9) ; extra == 'tests'
Requires-Dist: flake8 (<7,>=4) ; extra == 'tests'
Requires-Dist: flake8-builtins (<3,>=1.5) ; extra == 'tests'
Requires-Dist: flake8-colors (<0.2,>=0.1) ; extra == 'tests'
Requires-Dist: flake8-docstrings (<2,>=1.5) ; extra == 'tests'
Requires-Dist: flake8-rst-docstrings (<0.4,>=0.2) ; extra == 'tests'
Requires-Dist: flake8-use-fstring (<2,>=1) ; extra == 'tests'
Requires-Dist: fsspec[http] ; extra == 'tests'
Requires-Dist: intake (<0.7,>=0.6.5) ; extra == 'tests'
Requires-Dist: mccabe (<0.8,>=0.6) ; extra == 'tests'
Requires-Dist: msgpack-numpy (<0.5,>=0.4) ; extra == 'tests'
Requires-Dist: mypy (>=0.942) ; extra == 'tests'
Requires-Dist: pandas (<2,>=1.4) ; extra == 'tests'
Requires-Dist: pep8-naming (<0.14,>=0.12) ; extra == 'tests'
Requires-Dist: pre-commit (<3,>=2.9) ; extra == 'tests'
Requires-Dist: pydocstyle (<7,>=5.1) ; extra == 'tests'
Requires-Dist: pytest (<8,>=6.2) ; extra == 'tests'
Requires-Dist: pytest-cov (<5.0,>=2.10) ; extra == 'tests'
Requires-Dist: rstcheck[sphinx] (<7,>=5) ; extra == 'tests'
Requires-Dist: sqlalchemy (<2,>=1.3) ; extra == 'tests'
Requires-Dist: tox (<4,>=3.20) ; extra == 'tests'
Provides-Extra: types
Requires-Dist: types-setuptools ; extra == 'types'
